fhir_validator/__init__.py
fhir_validator/validator.py
fhir_validator-0.2.2.dist-info/LICENSE
fhir_validator-0.2.2.dist-info/METADATA
fhir_validator-0.2.2.dist-info/WHEEL
fhir_validator-0.2.2.dist-info/entry_points.txt
fhir_validator-0.2.2.dist-info/RECORD
