Metadata-Version: 2.1
Name: fhir-validator
Version: 0.2.2
Summary: FHIR Validator and Identifier for resource vs bundle type
Home-page: https://github.com/thevgergroup/fhir-validator
License: MIT
Keywords: FHIR,HL7,validator,identifier
Author: patrick o'leary
Author-email: pjaol@pjaol.com
Requires-Python: >=3.9,<3.12
Classifier: Intended Audience :: Healthcare Industry
Classifier: License :: OSI Approved :: MIT License
Classifier: Programming Language :: Python :: 3
Classifier: Programming Language :: Python :: 3.9
Classifier: Programming Language :: Python :: 3.10
Classifier: Programming Language :: Python :: 3.11
Requires-Dist: fastjsonschema (>=2.20.0,<3.0.0)
Project-URL: Repository, https://github.com/thevgergroup/fhir-validator.git
